pva_resimagenet/__init__.py
pva_resimagenet/net.py
pva_resimagenet/trained_net/ResImageNet.pth
pva_resimagenet-0.0.9.dist-info/LICENSE
pva_resimagenet-0.0.9.dist-info/METADATA
pva_resimagenet-0.0.9.dist-info/WHEEL
pva_resimagenet-0.0.9.dist-info/top_level.txt
pva_resimagenet-0.0.9.dist-info/RECORD
