Metadata-Version: 2.1
Name: pva-resimagenet
Version: 0.0.9
Summary: NN based on U-Net and DenseNet for image restoration
Home-page: https://github.com/Tailtoon/ResImageNet
Author: Vadim Pashkin
Author-email: vaplev@mail.ru
Project-URL: Bug Tracker, https://github.com/Tailtoon/ResImageNet/issues
Classifier: Development Status :: 3 - Alpha
Classifier: Programming Language :: Python :: 3
Classifier: License :: OSI Approved :: BSD License
Classifier: Operating System :: OS Independent
Requires-Python: ==3.8.10
License-File: LICENSE
Requires-Dist: scikit-image
Requires-Dist: matplotlib
Requires-Dist: torch
Requires-Dist: torchvision
Requires-Dist: torchaudio
Requires-Dist: torchinfo
